pokerdf/__init__.py
pokerdf/core/read_and_convert.py
pokerdf/main.py
pokerdf/regex/regex_execution.py
pokerdf/regex/regex_patterns.py
pokerdf/utils/strings.py
pokerdf/validation/pydantic_modules.py
pokerdf-1.0.6.dist-info/LICENSE
pokerdf-1.0.6.dist-info/METADATA
pokerdf-1.0.6.dist-info/WHEEL
pokerdf-1.0.6.dist-info/entry_points.txt
pokerdf-1.0.6.dist-info/RECORD
