Metadata-Version: 2.3
Name: pokerdf
Version: 1.0.6
Summary: Converts poker hand history files to pandas DataFrames.
Author: Murilo Amaral
Author-email: murilogmamaral@gmail.com
Requires-Python: >=3.11.5
Classifier: Programming Language :: Python :: 3
Classifier: Programming Language :: Python :: 3.12
Classifier: Programming Language :: Python :: 3.13
Requires-Dist: joblib (==1.3.2)
Requires-Dist: mypy (>=0.0.0)
Requires-Dist: pandas (>=2.0.0)
Requires-Dist: pyarrow (>=16.1.0)
Requires-Dist: pydantic (>=2.8.0)
Requires-Dist: ruff (>=0.0.0)
Project-URL: repository, https://github.com/murilogmamaral/pokerdf
